syngenta_digital_dta/__init__.py
syngenta_digital_dta/common/__init__.py
syngenta_digital_dta/common/base_adapter.py
syngenta_digital_dta/common/dict_merger.py
syngenta_digital_dta/common/json_helper.py
syngenta_digital_dta/common/logger.py
syngenta_digital_dta/common/publisher.py
syngenta_digital_dta/common/schema_loader.py
syngenta_digital_dta/common/schema_mapper.py
syngenta_digital_dta/dynamodb/__init__.py
syngenta_digital_dta/dynamodb/adapter.py
syngenta_digital_dta/elasticsearch/__init__.py
syngenta_digital_dta/elasticsearch/adapter.py
syngenta_digital_dta/elasticsearch/es_connection.py
syngenta_digital_dta/elasticsearch/es_connector.py
syngenta_digital_dta/elasticsearch/es_mapper.py
syngenta_digital_dta/file_system/__init__.py
syngenta_digital_dta/file_system/adapter.py
syngenta_digital_dta/mongo/__init__.py
syngenta_digital_dta/mongo/adapter.py
syngenta_digital_dta/postgres/__init__.py
syngenta_digital_dta/postgres/adapter.py
syngenta_digital_dta/postgres/json_formatting.py
syngenta_digital_dta/postgres/sql_connection.py
syngenta_digital_dta/postgres/sql_connector.py
syngenta_digital_dta/s3/__init__.py
syngenta_digital_dta/s3/adapter.py
tests/__init__.py
tests/syngenta_digital_dta/__init__.py
tests/syngenta_digital_dta/test__init__.py
tests/syngenta_digital_dta/common/__init__.py
tests/syngenta_digital_dta/common/test_base_adapter.py
tests/syngenta_digital_dta/common/test_dict_merger.py
tests/syngenta_digital_dta/common/test_publisher.py
tests/syngenta_digital_dta/common/test_schema_mapper.py
tests/syngenta_digital_dta/dynamodb/__init__.py
tests/syngenta_digital_dta/dynamodb/mock_table.py
tests/syngenta_digital_dta/dynamodb/test_adapter.py
tests/syngenta_digital_dta/elasticsearch/__init__.py
tests/syngenta_digital_dta/elasticsearch/mocks.py
tests/syngenta_digital_dta/elasticsearch/test_adapter.py
tests/syngenta_digital_dta/elasticsearch/test_es_connector.py
tests/syngenta_digital_dta/elasticsearch/test_es_mapper.py
syngenta_digital_dta-0.1.14.dist-info/LICENSE
syngenta_digital_dta-0.1.14.dist-info/METADATA
syngenta_digital_dta-0.1.14.dist-info/WHEEL
syngenta_digital_dta-0.1.14.dist-info/top_level.txt
syngenta_digital_dta-0.1.14.dist-info/RECORD
