Metadata-Version: 2.1
Name: syngenta_digital_dta
Version: 0.1.14
Summary: A DRY multi-database normalizer.
Home-page: https://github.com/syngenta-digital/package-python-dta.git
Author: Paul Cruse III, Engineering Lead, Syngenta Digital
Author-email: paul.cruse@syngenta.com
Classifier: Environment :: Web Environment
Classifier: Intended Audience :: Developers
Classifier: Topic :: Internet :: WWW/HTTP :: Dynamic Content
Classifier: Topic :: Software Development :: Libraries :: Python Modules
Classifier: Programming Language :: Python
Classifier: Programming Language :: Python :: 3
Classifier: Programming Language :: Python :: 3.6
Classifier: Programming Language :: Python :: 3.7
Requires-Python: >=3.0
License-File: LICENSE
Requires-Dist: boto3
Requires-Dist: elasticsearch ==7.13.4
Requires-Dist: jsonref
Requires-Dist: jsonpickle
Requires-Dist: pyyaml
Requires-Dist: requests-aws4auth
Requires-Dist: simplejson
